tests/__init__.py
tests/test_Possibly.py
tests/test_Safely.py
tests/test_add_columns.py
tests/test_apply_cum.py
tests/test_apply_window.py
tests/test_bulk_insert.py
tests/test_coalesce.py
tests/test_combination.py
tests/test_copy_table_schema.py
tests/test_create_table.py
tests/test_create_table_object.py
tests/test_drop_table.py
tests/test_fit_dataframe_to_table_schema.py
tests/test_flatten_dict.py
tests/test_gather.py
tests/test_get_batch_dataframe.py
tests/test_get_create_table_script.py
tests/test_load_table_schema.py
tests/test_nest.py
tests/test_nvl.py
tests/test_reorder_columns.py
tests/test_rolling.py
tests/test_select.py
tests/test_separate.py
tests/test_spead.py
tests/test_spread.py
tests/test_string.py
tests/test_strip_whitespace.py
tests/test_strip_whitespace_include_newline.py
tests/test_to_dataframe.py
tests/test_unnest.py
tidyframe/__init__.py
tidyframe/cature.py
tidyframe/nest.py
tidyframe/reshape.py
tidyframe/transform.py
tidyframe/unnest.py
tidyframe/tests/__init__.py
tidyframe/tests/test_Possibly.py
tidyframe/tests/test_Safely.py
tidyframe/tests/test_apply_partition.py
tidyframe/tests/test_apply_window.py
tidyframe/tests/test_gather.py
tidyframe/tests/test_nest.py
tidyframe/tests/test_spead.py
tidyframe/tests/test_unnest.py
tidyframe/tools/__init__.py
tidyframe/tools/case_when.py
tidyframe/tools/combination.py
tidyframe/tools/database.py
tidyframe/tools/dict.py
tidyframe/tools/select.py
tidyframe/tools/separate.py
tidyframe/tools/string.py
tidyframe/tools/window.py
tidyframe-0.0.3.dist-info/DESCRIPTION.rst
tidyframe-0.0.3.dist-info/METADATA
tidyframe-0.0.3.dist-info/RECORD
tidyframe-0.0.3.dist-info/WHEEL
tidyframe-0.0.3.dist-info/metadata.json
tidyframe-0.0.3.dist-info/top_level.txt
